datateer_upload_agent/__init__.py
datateer_upload_agent/config.py
datateer_upload_agent/constants.py
datateer_upload_agent/main.py
datateer_upload_agent/uploader/upload.py
datateer_upload_agent/uploader/upload_gcs.py
datateer_upload_agent/uploader/upload_s3.py
datateer_upload_agent-0.5.1.dist-info/LICENSE
datateer_upload_agent-0.5.1.dist-info/METADATA
datateer_upload_agent-0.5.1.dist-info/WHEEL
datateer_upload_agent-0.5.1.dist-info/entry_points.txt
datateer_upload_agent-0.5.1.dist-info/RECORD
