Metadata-Version: 2.1
Name: datateer-upload-agent
Version: 0.5.1
Summary: An agent that can be installed inside a firewall or VPN and used to push data to Datateer
Author: Datateer
Author-email: dev@datateer.com
Requires-Python: >=3.8,<4.0
Classifier: Programming Language :: Python :: 3
Classifier: Programming Language :: Python :: 3.8
Classifier: Programming Language :: Python :: 3.9
Classifier: Programming Language :: Python :: 3.10
Classifier: Programming Language :: Python :: 3.11
Requires-Dist: PyYAML (==6.0.1)
Requires-Dist: boto3 (>=1.20.49,<2.0.0)
Requires-Dist: click (>=8.0.3,<9.0.0)
Requires-Dist: coverage (>=6.5.0,<7.0.0)
Requires-Dist: gcloud (>=0.18.3,<0.19.0)
